Workbook

Sheet Sheet1
A2: Item Name | B2: Size | C2: Average Purchase Rate | D2: Estimated Mrp
A3: 06 Rose Vodka | B3: 750-650 ML | C3: 5331.23 | D3: 5980 | G3: 750/650ML | H3: 375/500ML | I3: 180/330ML | J3: 90ML
A4: 100 Pipers 12 Yo Blended Scotch | B4: 180-330 ML | C4: 532.94 | D4: 600
A5: 100 Pipers 12 Yo Blended Scotch | B5: 750-650 ML | C5: 2141.14 | D5: 2400
A6: 100 Pipers Scotch | B6: 180-330 ML | C6: 368.75 | D6: 420
A7: 100 Pipers Scotch | B7: 375-500 ML | C7: 754.58 | D7: 850
A8: 100 Pipers Scotch | B8: 750-650 ML | C8: 1498.23 | D8: 1680
A9: 100 Pipers Scotch 8 Year | B9: 180-330 ML | C9: 515.14 | D9: 580
A10: 100 Pipers Scotch 8 Year | B10: 750-650 ML | C10: 2054.72 | D10: 2310
A11: 1943 Virasat Indian Whisky | B11: 750-650 ML | C11: 4077.84 | D11: 4570
A12: 1965 Espresso Coffee Premium Dark Rum | B12: 180-330 ML | C12: 215.51 | D12: 250
A13: 1965 Espresso Coffee Premium Dark Rum | B13: 375-500 ML | C13: 428.98 | D13: 490
A14: 1965 Espresso Coffee Premium Dark Rum | B14: 750-650 ML | C14: 847.95 | D14: 950
A15: 1965 Lemon Dash Rum | B15: 180-330 ML | C15: 177.26 | D15: 200
... A1077: Wonder Wine | B1077: 180-330 ML | C1077: 161.09 | D1077: 190

Sheet Sheet4
B2: name | C2: code
B3: 90 ML | C3: 10002
B4: 750-650 ML | C4: 10019
B5: 375-500 ML | C5: 10020
B6: 180-330 ML | C6: 10021

Sheet Sheet2
A1: Item Code | B1: Item Name | C1: Brand Code | D1: Category Code | E1: MRP | F1: Purchase Price | G1: Size | H1: StatuS | I1: Size Name | J1: Code
A2: 10022 | B2: 06 Rose Vodka | C2: 10018 | D2: 10014 | H2: 1 | I2: 750-650 ML | J2: =VLOOKUP(I2,Sheet4!B:C,2,) -> 10019 | K2: 5331.23 | L2: 5980
A3: =A2+1 -> 10023 | B3: 100 Pipers 12 Yo Blended Scotch | C3: 10018 | D3: 10014 | H3: 1 | I3: 180-330 ML | J3: =VLOOKUP(I3,Sheet4!B:C,2,) -> 10021 | K3: 532.94 | L3: 600
A4: =A3+1 -> 10024 | B4: 100 Pipers 12 Yo Blended Scotch | C4: 10018 | D4: 10014 | H4: 1 | I4: 750-650 ML | J4: =VLOOKUP(I4,Sheet4!B:C,2,) -> 10019 | K4: 2141.14 | L4: 2400
A5: =A4+1 -> 10025 | B5: 100 Pipers Scotch | C5: 10018 | D5: 10014 | H5: 1 | I5: 180-330 ML | J5: =VLOOKUP(I5,Sheet4!B:C,2,) -> 10021 | K5: 368.75 | L5: 420
A6: =A5+1 -> 10026 | B6: 100 Pipers Scotch | C6: 10018 | D6: 10014 | H6: 1 | I6: 375-500 ML | J6: =VLOOKUP(I6,Sheet4!B:C,2,) -> 10020 | K6: 754.58 | L6: 850
A7: =A6+1 -> 10027 | B7: 100 Pipers Scotch | C7: 10018 | D7: 10014 | H7: 1 | I7: 750-650 ML | J7: =VLOOKUP(I7,Sheet4!B:C,2,) -> 10019 | K7: 1498.23 | L7: 1680
A8: =A7+1 -> 10028 | B8: 100 Pipers Scotch 8 Year | C8: 10018 | D8: 10014 | H8: 1 | I8: 180-330 ML | J8: =VLOOKUP(I8,Sheet4!B:C,2,) -> 10021 | K8: 515.14 | L8: 580
A9: =A8+1 -> 10029 | B9: 100 Pipers Scotch 8 Year | C9: 10018 | D9: 10014 | H9: 1 | I9: 750-650 ML | J9: =VLOOKUP(I9,Sheet4!B:C,2,) -> 10019 | K9: 2054.72 | L9: 2310
A10: =A9+1 -> 10030 | B10: 1943 Virasat Indian Whisky | C10: 10018 | D10: 10014 | H10: 1 | I10: 750-650 ML | J10: =VLOOKUP(I10,Sheet4!B:C,2,) -> 10019 | K10: 4077.84 | L10: 4570
A11: =A10+1 -> 10031 | B11: 1965 Espresso Coffee Premium Dark Rum | C11: 10018 | D11: 10014 | H11: 1 | I11: 180-330 ML | J11: =VLOOKUP(I11,Sheet4!B:C,2,) -> 10021 | K11: 215.51 | L11: 250
A12: =A11+1 -> 10032 | B12: 1965 Espresso Coffee Premium Dark Rum | C12: 10018 | D12: 10014 | H12: 1 | I12: 375-500 ML | J12: =VLOOKUP(I12,Sheet4!B:C,2,) -> 10020 | K12: 428.98 | L12: 490
A13: =A12+1 -> 10033 | B13: 1965 Espresso Coffee Premium Dark Rum | C13: 10018 | D13: 10014 | H13: 1 | I13: 750-650 ML | J13: =VLOOKUP(I13,Sheet4!B:C,2,) -> 10019 | K13: 847.95 | L13: 950
A14: =A13+1 -> 10034 | B14: 1965 Lemon Dash Rum | C14: 10018 | D14: 10014 | H14: 1 | I14: 180-330 ML | J14: =VLOOKUP(I14,Sheet4!B:C,2,) -> 10021 | K14: 177.26 | L14: 200
... A1076: =A1075+1 -> 11096 | B1076: Wonder Wine | C1076: 10018 | D1076: 10014 | H1076: 1 | I1076: 180-330 ML | J1076: =VLOOKUP(I1076,Sheet4!B:C,2,) -> 10021 | K1076: 161.09 | L1076: 190

Sheet Sheet3
